markdown2app/__init__.py
markdown2app/__main__.py
markdown2app/_version.py
markdown2app/config/__init__.py
markdown2app-0.1.8.dist-info/licenses/LICENSE
markdown2app-0.1.8.dist-info/METADATA
markdown2app-0.1.8.dist-info/WHEEL
markdown2app-0.1.8.dist-info/top_level.txt
markdown2app-0.1.8.dist-info/RECORD
