Metadata-Version: 2.4
Name: markdown2app
Version: 0.1.8
Summary: libs to run markdown as an app in a python3 environment
Home-page: https://markdown2app.plainmark.com
Author: Tom Sapletta
Author-email: tom@sapletta.com
Maintainer: markdown2app developers
Maintainer-email: info@softreck.dev
License: Apache-2.0
Project-URL: Repository, https://github.com/plain-mark/markdown2app
Project-URL: Changelog, https://github.com/plain-mark/markdown2app/releases
Project-URL: Wiki, https://github.com/plain-mark/markdown2app/wiki
Project-URL: Issue Tracker, https://github.com/plain-mark/markdown2app/issues/new
Keywords: python,markdown2app,markdown,app,plainmark
Classifier: License :: OSI Approved :: Apache Software License
Classifier: Programming Language :: Python
Classifier: Programming Language :: Python :: 3
Classifier: Programming Language :: Python :: 3.7
Classifier: Programming Language :: Python :: 3.8
Classifier: Programming Language :: Python :: 3.9
Classifier: Programming Language :: Python :: 3.10
Classifier: Programming Language :: Python :: 3.11
Requires-Python: >=3.7
License-File: LICENSE
Dynamic: author
Dynamic: author-email
Dynamic: classifier
Dynamic: description
Dynamic: description-content-type
Dynamic: home-page
Dynamic: keywords
Dynamic: license
Dynamic: license-file
Dynamic: maintainer
Dynamic: maintainer-email
Dynamic: project-url
Dynamic: requires-python
Dynamic: summary
